FPU/verilog/bsl_tb.v
`timescale 1ns/1ps

module bsl_tb;

reg [4:0] a;
reg [31:0] b;
initial begin
    $dumpfile("bsl_tb.vcd");
    $dumpvars;
    a = 0;
    b = 32'hDEADBEEF;
    #1 a=a+1;
    #1 a=a+1;
    #1 a=a+1;
    #1 a=a+1;
    #1 a=a+1;
    #1 a=a+1;
    #1 a=a+1;
    #1 a=a+1;
    #1 a=a+1;
    #1 a=a+1;
    #1 a=a+1;
    #1 a=a+1;
    #1 a=a+1;
    $finish;
end

wire [31:0] dout_sr;
wire [31:0] dout_sr_ref = b>>a;
wire [31:0] dout_sl;
wire [31:0] dout_sl_ref = b<<a;

bsr #(.SWIDTH(5)) dur(
    .din(b),
    .s(a),
    .filler(1'b0),
    .dout(dout_sr)
);

bsl #(.SWIDTH(5)) dul(
    .din(b),
    .s(a),
    .filler(1'b0),
    .dout(dout_sl)
);

endmodule /* bsl_tb */

FPU/verilog/misc.v
// Misc Building Blocks
// Anhang Li Nov.19 2021

`timescale 1ns/1ps

// Exchanger
module xchg #(
	parameter DWIDTH = 32
)(
	input [DWIDTH-1:0]  ia,
	input [DWIDTH-1:0]  ib,
	input               xchg,
	output [DWIDTH-1:0] oa,
	output [DWIDTH-1:0] ob
);

assign oa = xchg ? ib : ia;
assign ob = xchg ? ia : ib;

endmodule /* xchg */

// Parametrized Barrel Shifter : Right Shift
module bsr #(
	parameter SWIDTH = 5
)(
	input [(2**SWIDTH)-1:0]     din,
	input [SWIDTH-1:0]          s,
	input                       filler, // 0:        SRL Logic  Shift Right
										// din[MSB]: SRA Arith. Shift Right (preserve sign)
	output [(2**SWIDTH)-1:0]    dout
);

wire [(2**SWIDTH)-1:0]	temp [SWIDTH:0];

assign temp[0] = din;
assign dout    = temp[SWIDTH];

genvar gi;
generate
	for(gi=0;gi<SWIDTH;gi=gi+1) begin : gen_brshift
		assign temp[gi+1] = s[gi] ? {{(2**gi){filler}},temp[gi]>>(2**gi)} : temp[gi];
	end
endgenerate

endmodule   /* bsr */

// Parametrized Barrel Shifter: Left Shift
module bsl #(
	parameter SWIDTH = 5
)(
	input [(2**SWIDTH)-1:0]     din,
	input [SWIDTH-1:0]          s,
	input                       filler, // 0: SLL Logic  Shift Left
	output [(2**SWIDTH)-1:0]    dout
);

wire [(2**SWIDTH)-1:0]	temp [SWIDTH:0];

assign temp[0] = din;
assign dout    = temp[SWIDTH];

genvar gi;
generate
	for(gi=0;gi<SWIDTH;gi=gi+1) begin : gen_blshift
		assign temp[gi+1] = s[gi] ? {temp[gi],{(2**gi){filler}}} : temp[gi];
	end
endgenerate

endmodule   /* bsl */

/*
module bsr_tb;
    reg [31:0] din;
    reg [4:0]  s;
    wire [31:0] dout;
    bsr #(.SWIDTH(32)) dut(
        .din(din),
        .s(s),
        .filler(1'b0),
        .dout(dout)
    );
  initial 
    begin
        din = 32'hDEADBEEF;
        s   = 31;
        #1
        $display("%d,%d,%d,%d",din,s,din>>s,dout);
    end
endmodule /* brshift_tb */

// Counting Lead Zero using a tree structure
// https://electronics.stackexchange.com/questions/196914/verilog-synthesize-high-speed-leading-zero-count
module count_lead_zero #(
    parameter W_IN = 32,           // Must be power of 2, >=2
    parameter W_OUT = $clog2(W_IN) // Let this default
) (
    input wire  [W_IN-1:0] in,
    output wire [W_OUT-1:0] out
);

generate
	if (W_IN > 2) begin : gen_recurse
		wire [W_OUT-2:0] half_count;
		wire [W_IN / 2-1:0] lhs = in[W_IN / 2 +: W_IN / 2];
		wire [W_IN / 2-1:0] rhs = in[0        +: W_IN / 2];
		wire left_empty = ~|lhs;

		count_lead_zero #(
			.W_IN (W_IN / 2)
		) inner (
			.in  (left_empty ? rhs : lhs),
			.out (half_count)
		);
		assign out = {left_empty, half_count};
	end else begin : gen_terminal
		assign out = !in[1];
	end
endgenerate

endmodule /* count_lead_zero */

module booth_enc_r4(
	input      [2:0]	bin,
	output reg [2:0]	br4_out
);

localparam  BOOTH_0  = 3'b000;
localparam  BOOTH_P1 = 3'b001;
localparam  BOOTH_P2 = 3'b010;
localparam  BOOTH_N1 = 3'b111;
localparam  BOOTH_N2 = 3'b110;

always @* begin
	br4_out = 3'bxxx;
	case(bin)
		3'b000: br4_out = BOOTH_0;
		3'b001: br4_out = BOOTH_P1;
		3'b010: br4_out = BOOTH_P1;
		3'b011: br4_out = BOOTH_P2;
		3'b100: br4_out = BOOTH_N2;
		3'b101: br4_out = BOOTH_N1;
		3'b110: br4_out = BOOTH_N1;
		3'b111: br4_out = BOOTH_0;
	endcase
end

endmodule

// fpga4student.com FPGA projects, Verilog projects, VHDL projects 
// Verilog code for carry look-ahead adder
module cla_adder #(
	parameter DATA_WID = 32
)(
	input wire  [DATA_WID - 1:0]  in1,
	input wire  [DATA_WID - 1:0]  in2,
	input wire                    carry_in,
	output wire [DATA_WID - 1:0]  sum,
	output wire                   carry_out
);
	//assign {carry_out, sum} = in1 + in2 + carry_in;
	wire [DATA_WID - 1:0] gen;
	wire [DATA_WID - 1:0] pro;
	wire [DATA_WID:0] carry_tmp;
	genvar j, i;
	generate
		//assume carry_tmp in is zero
		assign carry_tmp[0] = carry_in;
		//carry generator
		for(j = 0; j < DATA_WID; j = j + 1) begin: carry_generator
			assign gen[j] = in1[j] & in2[j];
			assign pro[j] = in1[j] | in2[j];
			assign carry_tmp[j+1] = gen[j] | pro[j] & carry_tmp[j];
		end 
		//carry out 
		assign carry_out = carry_tmp[DATA_WID];
		//calculate sum 
		//assign sum[0] = in1[0] ^ in2 ^ carry_in;
		for(i = 0; i < DATA_WID; i = i+1) begin: sum_without_carry
			assign sum[i] = in1[i] ^ in2[i] ^ carry_tmp[i];
		end 
	endgenerate 
endmodule

// Radix-4 Booth Partial Product Generator
module booth_ppgen_r4 #(
	parameter DWIDTH = 11
)(
	input [DWIDTH-1:0]			a,
	input [2:0]					br4,
	output reg [DWIDTH:0]		o,
	output                      s
);
	assign s = br4[2];
	always @* begin
		o = {(DWIDTH){1'bx}};
		case(br4)
		3'b000: o = 0;
		3'b001:	o = {1'b0,a};
		3'b010: o = {a,1'b0};
		3'b111:	o = {1'b1,~a};
		3'b110: o = {~a,1'b1};
		endcase
	end
endmodule /* booth_ppgen_r4 */

FPU/icverilog/bsl_tb.vcd
$date
	Fri Nov 26 18:45:35 2021
$end
$version
	Icarus Verilog
$end
$timescale
	1ps
$end
$scope module booth_enc_r4 $end
$var wire 3 ! bin [2:0] $end
$var reg 3 " br4_out [2:0] $end
$upscope $end
$scope module booth_ppgen_r4 $end
$var wire 11 # a [10:0] $end
$var wire 3 $ br4 [2:0] $end
$var wire 1 % s $end
$var reg 12 & o [11:0] $end
$upscope $end
$scope module bsl_tb $end
$var wire 32 ' dout_sr_ref [31:0] $end
$var wire 32 ( dout_sr [31:0] $end
$var wire 32 ) dout_sl_ref [31:0] $end
$var wire 32 * dout_sl [31:0] $end
$var reg 5 + a [4:0] $end
$var reg 32 , b [31:0] $end
$scope module dul $end
$var wire 32 - din [31:0] $end
$var wire 32 . dout [31:0] $end
$var wire 1 / filler $end
$var wire 5 0 s [4:0] $end
$scope begin gen_blshift[0] $end
$upscope $end
$scope begin gen_blshift[1] $end
$upscope $end
$scope begin gen_blshift[2] $end
$upscope $end
$scope begin gen_blshift[3] $end
$upscope $end
$scope begin gen_blshift[4] $end
$upscope $end
$upscope $end
$scope module dur $end
$var wire 32 1 din [31:0] $end
$var wire 32 2 dout [31:0] $end
$var wire 1 3 filler $end
$var wire 5 4 s [4:0] $end
$scope begin gen_brshift[0] $end
$upscope $end
$scope begin gen_brshift[1] $end
$upscope $end
$scope begin gen_brshift[2] $end
$upscope $end
$scope begin gen_brshift[3] $end
$upscope $end
$scope begin gen_brshift[4] $end
$upscope $end
$upscope $end
$upscope $end
$scope module cla_adder $end
$var wire 1 5 carry_in $end
$var wire 32 6 in1 [31:0] $end
$var wire 32 7 in2 [31:0] $end
$var wire 32 8 sum [31:0] $end
$var wire 32 9 pro [31:0] $end
$var wire 32 : gen [31:0] $end
$var wire 33 ; carry_tmp [32:0] $end
$var wire 1 < carry_out $end
$scope begin carry_generator[0] $end
$upscope $end
$scope begin carry_generator[1] $end
$upscope $end
$scope begin carry_generator[2] $end
$upscope $end
$scope begin carry_generator[3] $end
$upscope $end
$scope begin carry_generator[4] $end
$upscope $end
$scope begin carry_generator[5] $end
$upscope $end
$scope begin carry_generator[6] $end
$upscope $end
$scope begin carry_generator[7] $end
$upscope $end
$scope begin carry_generator[8] $end
$upscope $end
$scope begin carry_generator[9] $end
$upscope $end
$scope begin carry_generator[10] $end
$upscope $end
$scope begin carry_generator[11] $end
$upscope $end
$scope begin carry_generator[12] $end
$upscope $end
$scope begin carry_generator[13] $end
$upscope $end
$scope begin carry_generator[14] $end
$upscope $end
$scope begin carry_generator[15] $end
$upscope $end
$scope begin carry_generator[16] $end
$upscope $end
$scope begin carry_generator[17] $end
$upscope $end
$scope begin carry_generator[18] $end
$upscope $end
$scope begin carry_generator[19] $end
$upscope $end
$scope begin carry_generator[20] $end
$upscope $end
$scope begin carry_generator[21] $end
$upscope $end
$scope begin carry_generator[22] $end
$upscope $end
$scope begin carry_generator[23] $end
$upscope $end
$scope begin carry_generator[24] $end
$upscope $end
$scope begin carry_generator[25] $end
$upscope $end
$scope begin carry_generator[26] $end
$upscope $end
$scope begin carry_generator[27] $end
$upscope $end
$scope begin carry_generator[28] $end
$upscope $end
$scope begin carry_generator[29] $end
$upscope $end
$scope begin carry_generator[30] $end
$upscope $end
$scope begin carry_generator[31] $end
$upscope $end
$scope begin sum_without_carry[0] $end
$upscope $end
$scope begin sum_without_carry[1] $end
$upscope $end
$scope begin sum_without_carry[2] $end
$upscope $end
$scope begin sum_without_carry[3] $end
$upscope $end
$scope begin sum_without_carry[4] $end
$upscope $end
$scope begin sum_without_carry[5] $end
$upscope $end
$scope begin sum_without_carry[6] $end
$upscope $end
$scope begin sum_without_carry[7] $end
$upscope $end
$scope begin sum_without_carry[8] $end
$upscope $end
$scope begin sum_without_carry[9] $end
$upscope $end
$scope begin sum_without_carry[10] $end
$upscope $end
$scope begin sum_without_carry[11] $end
$upscope $end
$scope begin sum_without_carry[12] $end
$upscope $end
$scope begin sum_without_carry[13] $end
$upscope $end
$scope begin sum_without_carry[14] $end
$upscope $end
$scope begin sum_without_carry[15] $end
$upscope $end
$scope begin sum_without_carry[16] $end
$upscope $end
$scope begin sum_without_carry[17] $end
$upscope $end
$scope begin sum_without_carry[18] $end
$upscope $end
$scope begin sum_without_carry[19] $end
$upscope $end
$scope begin sum_without_carry[20] $end
$upscope $end
$scope begin sum_without_carry[21] $end
$upscope $end
$scope begin sum_without_carry[22] $end
$upscope $end
$scope begin sum_without_carry[23] $end
$upscope $end
$scope begin sum_without_carry[24] $end
$upscope $end
$scope begin sum_without_carry[25] $end
$upscope $end
$scope begin sum_without_carry[26] $end
$upscope $end
$scope begin sum_without_carry[27] $end
$upscope $end
$scope begin sum_without_carry[28] $end
$upscope $end
$scope begin sum_without_carry[29] $end
$upscope $end
$scope begin sum_without_carry[30] $end
$upscope $end
$scope begin sum_without_carry[31] $end
$upscope $end
$upscope $end
$scope module xchg $end
$var wire 32 = ia [31:0] $end
$var wire 32 > ib [31:0] $end
$var wire 1 ? xchg $end
$var wire 32 @ ob [31:0] $end
$var wire 32 A oa [31:0] $end
$upscope $end
$enddefinitions $end
#0
$dumpvars
bz A
bz @
z?
bz >
bz =
x<
bxz ;
bx :
bx 9
bx 8
bz 7
bz 6
z5
b0 4
03
b11011110101011011011111011101111 2
b11011110101011011011111011101111 1
b0 0
0/
b11011110101011011011111011101111 .
b11011110101011011011111011101111 -
b11011110101011011011111011101111 ,
b0 +
b11011110101011011011111011101111 *
b11011110101011011011111011101111 )
b11011110101011011011111011101111 (
b11011110101011011011111011101111 '
b0xxxxxxxxxxx &
z%
bz $
bz #
bx "
bz !
$end
#1000
b10111101010110110111110111011110 *
b10111101010110110111110111011110 .
b1101111010101101101111101110111 (
b1101111010101101101111101110111 2
b1101111010101101101111101110111 '
b10111101010110110111110111011110 )
b1 +
b1 0
b1 4
#2000
b1111010101101101111101110111100 *
b1111010101101101111101110111100 .
b110111101010110110111110111011 (
b110111101010110110111110111011 2
b110111101010110110111110111011 '
b1111010101101101111101110111100 )
b10 +
b10 0
b10 4
#3000
b11011110101011011011111011101 (
b11011110101011011011111011101 2
b11110101011011011111011101111000 *
b11110101011011011111011101111000 .
b11011110101011011011111011101 '
b11110101011011011111011101111000 )
b11 +
b11 0
b11 4
#4000
b11101010110110111110111011110000 *
b11101010110110111110111011110000 .
b1101111010101101101111101110 (
b1101111010101101101111101110 2
b1101111010101101101111101110 '
b11101010110110111110111011110000 )
b100 +
b100 0
b100 4
#5000
b110111101010110110111110111 (
b110111101010110110111110111 2
b11010101101101111101110111100000 *
b11010101101101111101110111100000 .
b110111101010110110111110111 '
b11010101101101111101110111100000 )
b101 +
b101 0
b101 4
#6000
b11011110101011011011111011 (
b11011110101011011011111011 2
b10101011011011111011101111000000 *
b10101011011011111011101111000000 .
b11011110101011011011111011 '
b10101011011011111011101111000000 )
b110 +
b110 0
b110 4
#7000
b1101111010101101101111101 (
b1101111010101101101111101 2
b1010110110111110111011110000000 *
b1010110110111110111011110000000 .
b1101111010101101101111101 '
b1010110110111110111011110000000 )
b111 +
b111 0
b111 4
#8000
b10101101101111101110111100000000 *
b10101101101111101110111100000000 .
b110111101010110110111110 (
b110111101010110110111110 2
b110111101010110110111110 '
b10101101101111101110111100000000 )
b1000 +
b1000 0
b1000 4
#9000
b11011110101011011011111 (
b11011110101011011011111 2
b1011011011111011101111000000000 *
b1011011011111011101111000000000 .
b11011110101011011011111 '
b1011011011111011101111000000000 )
b1001 +
b1001 0
b1001 4
#10000
b1101111010101101101111 (
b1101111010101101101111 2
b10110110111110111011110000000000 *
b10110110111110111011110000000000 .
b1101111010101101101111 '
b10110110111110111011110000000000 )
b1010 +
b1010 0
b1010 4
#11000
b110111101010110110111 (
b110111101010110110111 2
b1101101111101110111100000000000 *
b1101101111101110111100000000000 .
b110111101010110110111 '
b1101101111101110111100000000000 )
b1011 +
b1011 0
b1011 4
#12000
b11011110101011011011 (
b11011110101011011011 2
b11011011111011101111000000000000 *
b11011011111011101111000000000000 .
b11011110101011011011 '
b11011011111011101111000000000000 )
b1100 +
b1100 0
b1100 4
#13000
b1101111010101101101 (
b1101111010101101101 2
b10110111110111011110000000000000 *
b10110111110111011110000000000000 .
b1101111010101101101 '
b10110111110111011110000000000000 )
b1101 +
b1101 0
b1101 4
